diffdomain_py3/__init__.py
diffdomain_py3/classification.py
diffdomain_py3/diffdomains.py
diffdomain_py3/utils.py
diffDomain_py3-0.2.2.dist-info/LICENSE
diffDomain_py3-0.2.2.dist-info/METADATA
diffDomain_py3-0.2.2.dist-info/WHEEL
diffDomain_py3-0.2.2.dist-info/top_level.txt
diffDomain_py3-0.2.2.dist-info/RECORD
