Metadata-Version: 2.1
Name: diffDomain-py3
Version: 0.2.2
Summary: DiffDomain can test the significant difference of TADs on chromatin.
Home-page: https://github.com/Tian-Dechao/diffDomain
Author: Dechao Tian
Author-email: tiandch@mail.sysu.edu.cn
Classifier: Programming Language :: Python :: 3
Classifier: License :: OSI Approved :: MIT License
Classifier: Operating System :: OS Independent
License-File: LICENSE
Requires-Dist: hic-straw (==1.3.1)
Requires-Dist: cooler
Requires-Dist: hicexplorer
Requires-Dist: TracyWidom
Requires-Dist: pandas
Requires-Dist: numpy
Requires-Dist: docopt
Requires-Dist: statsmodels
Requires-Dist: tqdm
Requires-Dist: seaborn
Requires-Dist: matplotlib
Requires-Dist: h5py
